main.py
screens/__init__.py
screens/board.py
screens/kanban.tcss
screens/main_menu.py
widgets/__init__.py
widgets/card.py
terminal_kanban-0.1.1.dist-info/METADATA
terminal_kanban-0.1.1.dist-info/WHEEL
terminal_kanban-0.1.1.dist-info/entry_points.txt
terminal_kanban-0.1.1.dist-info/top_level.txt
terminal_kanban-0.1.1.dist-info/RECORD
