Metadata-Version: 2.4
Name: terminal-kanban
Version: 0.1.1
Summary: A terminal-based Kanban board
Author: Aryan
License-Expression: MIT
Requires-Python: >=3.9
Requires-Dist: textual
